flakyzavr/__init__.py
flakyzavr/_flakyzavr_plugin.py
flakyzavr/_jira_stdout.py
flakyzavr/_messages.py
flakyzavr/_traceback.py
flakyzavr/py.typed
flakyzavr/version
flakyzavr/version.py
flakyzavr-4.0.0.dist-info/licenses/LICENSE
flakyzavr-4.0.0.dist-info/METADATA
flakyzavr-4.0.0.dist-info/WHEEL
flakyzavr-4.0.0.dist-info/top_level.txt
flakyzavr-4.0.0.dist-info/RECORD
