Metadata-Version: 2.4
Name: flakyzavr
Version: 4.0.0
Summary: vedro.io plugin for reporting about flaky tests into jira (with plugin enabled in flaky check runs)
Home-page: https://github.com/ko10ok/flakyzavr
Author: Yuriy Sagitov
Author-email: pro100.ko10ok@gmail.com
License: Apache-2.0
Classifier: License :: OSI Approved :: Apache Software License
Classifier: Programming Language :: Python :: 3.10
Classifier: Typing :: Typed
Requires-Python: >=3.7
License-File: LICENSE
Requires-Dist: vedro<2.0,>=1.7
Requires-Dist: jira<3.11,>=3.10
Requires-Dist: rtry<2.0,>=1.4.0
Dynamic: author
Dynamic: author-email
Dynamic: classifier
Dynamic: description
Dynamic: description-content-type
Dynamic: home-page
Dynamic: license
Dynamic: license-file
Dynamic: requires-dist
Dynamic: requires-python
Dynamic: summary
